[
  {
    "id": 1,
    "name": "SUBRAMANIAN KR",
    "github_link": "https://github.com/Subramanian2006",
    "handles": {
      "leetcode": "SubramanianKR",
      "atcoder": "SubramanianKR",
      "codeforces": "krsubramanian2006",
      "hackerrank": "krsubramanian201",
      "github": "Subramanian2006",
      "skillrack": "SubramanianKR"
    }
  },
  {
    "id": 2,
    "name": "PRAKASH M S",
    "github_link": "https://github.com/Prakash-M-S",
    "handles": {
      "leetcode": "Prakash9545",
      "atcoder": "",
      "codeforces": "prakashsaravanan9545",
      "hackerrank": "prakashsaravana6",
      "github": "Prakash-M-S",
      "skillrack": "Prakash9545"
    }
  },
  {
    "id": 3,
    "name": "MADHAVAN P",
    "github_link": "https://github.com/Madhavan1302",
    "handles": {
      "leetcode": "madhavan0823",
      "atcoder": "Madhavan13",
      "codeforces": "madhavan0923",
      "hackerrank": "madhavan0923",
      "github": "Madhavan1302",
      "skillrack": "madhavan0823"
    }
  },
  {
    "id": 4,
    "name": "SHIVESH ELANGOVAN",
    "github_link": "https://github.com/elite1238",
    "handles": {
      "leetcode": "Shivesh_E",
      "atcoder": "ShiveshE",
      "codeforces": "shiveshe",
      "hackerrank": "elangoshivesh",
      "github": "elite1238",
      "skillrack": "Shivesh_E"
    }
  },
  {
    "id": 5,
    "name": "SENTHILNATHAN D",
    "github_link": "https://github.com/senthilnathand",
    "handles": {
      "leetcode": "senthilnathandhanabalan86",
      "atcoder": "Senthilnathan",
      "codeforces": "SENTHILNATHAN.DHANABALAN",
      "hackerrank": "senthilnathandh1",
      "github": "senthilnathand",
      "skillrack": "senthilnathandhanabalan86"
    }
  },
  {
    "id": 6,
    "name": "RAJAN B",
    "github_link": "https://github.com/rajanbalaji",
    "handles": {
      "leetcode": "rajanbalaji",
      "atcoder": "rajan2005",
      "codeforces": "rajanbalaji05",
      "hackerrank": "",
      "github": "rajanbalaji",
      "skillrack": "rajanbalaji"
    }
  },
  {
    "id": 7,
    "name": "YUVA D S",
    "github_link": "https://github.com/yuvareddy2005",
    "handles": {
      "leetcode": "Yuva_Reddy",
      "atcoder": "Yuva_Reddy",
      "codeforces": "yuvareddy2005",
      "hackerrank": "yuvareddy2005",
      "github": "yuvareddy2005",
      "skillrack": "Yuva_Reddy"
    }
  },
  {
    "id": 8,
    "name": "HARSHNI S",
    "github_link": "https://github.com/HarshniKannan100",
    "handles": {
      "leetcode": "HarshniKannan100",
      "atcoder": "Harshni100",
      "codeforces": "HarshniKannan100",
      "hackerrank": "harshnikannan100",
      "github": "HarshniKannan100",
      "skillrack": "HarshniKannan100"
    }
  },
  {
    "id": 9,
    "name": "VISHVESH ROSHAN S",
    "github_link": "https://github.com/VishveshRoshan",
    "handles": {
      "leetcode": "Vishvesh31",
      "atcoder": "Vishvesh31",
      "codeforces": "Vishvesh31",
      "hackerrank": "",
      "github": "VishveshRoshan",
      "skillrack": "Vishvesh31"
    }
  },
  {
    "id": 10,
    "name": "SRI HARI A",
    "github_link": "https://github.com/SrihariDB",
    "handles": {
      "leetcode": "fstHari",
      "atcoder": "kakashiHari",
      "codeforces": "sriharidharun2005",
      "hackerrank": "sriharidharun201",
      "github": "SrihariDB",
      "skillrack": "fstHari"
    }
  },
  {
    "id": 11,
    "name": "CIBANI JOE A",
    "github_link": "https://github.com/Cibani",
    "handles": {
      "leetcode": "wqZZoOVQet",
      "atcoder": "cibanijoe",
      "codeforces": "Cibani",
      "hackerrank": "cibanijoe",
      "github": "Cibani",
      "skillrack": "wqZZoOVQet"
    }
  },
  {
    "id": 12,
    "name": "ADITHYA A",
    "github_link": "https://github.com/Adithya-0606",
    "handles": {
      "leetcode": "AdithyaA_3006",
      "atcoder": "Adithya_3006",
      "codeforces": "adithya3006.a",
      "hackerrank": "",
      "github": "Adithya-0606",
      "skillrack": "AdithyaA_3006"
    }
  },
  {
    "id": 13,
    "name": "DEEPIKA P",
    "github_link": "https://github.com/Deepi-30",
    "handles": {
      "leetcode": "DeepikaPannirSelvam",
      "atcoder": "Deepika30Pannir",
      "codeforces": "deepikapannirt30",
      "hackerrank": "deepikapannirt30",
      "github": "Deepi-30",
      "skillrack": "DeepikaPannirSelvam"
    }
  },
  {
    "id": 14,
    "name": "SAMUEL FREDERICK NIRMAL E",
    "github_link": "https://github.com/samfnirmal",
    "handles": {
      "leetcode": "UjylaSVLGA",
      "atcoder": "samfnirmal_",
      "codeforces": "samfnirmal",
      "hackerrank": "samfnirmal",
      "github": "samfnirmal",
      "skillrack": "UjylaSVLGA"
    }
  },
  {
    "id": 15,
    "name": "RAKESH R",
    "github_link": "https://github.com/Rakesh-experience-web",
    "handles": {
      "leetcode": "",
      "atcoder": "",
      "codeforces": "",
      "hackerrank": "",
      "github": "Rakesh-experience-web",
      "skillrack": "rakeshr"
    }
  },
  {
    "id": 16,
    "name": "VIDHUSAN V",
    "github_link": "https://github.com/vidhusanv17",
    "handles": {
      "leetcode": "vidhusan_v",
      "atcoder": "nA0r7Pzpcp2wmsu6k",
      "codeforces": "vidhusan17",
      "hackerrank": "vidhusan17",
      "github": "vidhusanv17",
      "skillrack": "vidhusan_v"
    }
  },
  {
    "id": 17,
    "name": "ASHIK S",
    "github_link": "https://github.com/aashik2005",
    "handles": {
      "leetcode": "Ashik_3905",
      "atcoder": "ashik2005",
      "codeforces": "aashik2005",
      "hackerrank": "",
      "github": "aashik2005",
      "skillrack": "Ashik_3905"
    }
  },
  {
    "id": 18,
    "name": "LAKSHMANAN S",
    "github_link": "https://github.com/Lakshmanan195",
    "handles": {
      "leetcode": "lakshmanan23",
      "atcoder": "Lakshmanan",
      "codeforces": "slakshmananlm10",
      "hackerrank": "slakshmananlm10",
      "github": "Lakshmanan195",
      "skillrack": "lakshmanan23"
    }
  },
  {
    "id": 19,
    "name": "KATHIR G",
    "github_link": "https://github.com/Kathir2911",
    "handles": {
      "leetcode": "Kathir_2911",
      "atcoder": "Kathir_G",
      "codeforces": "Kathir_2911",
      "hackerrank": "Kathir2911",
      "github": "Kathir2911",
      "skillrack": "Kathir_2911"
    }
  },
  {
    "id": 20,
    "name": "ARLENE MONICA VINCY J",
    "github_link": "https://github.com/arlene3006",
    "handles": {
      "leetcode": "Arlene_0630",
      "atcoder": "arlene_3006",
      "codeforces": "arlenemonica_30",
      "hackerrank": "arlenemonica3006",
      "github": "arlene3006",
      "skillrack": "Arlene_0630"
    }
  },
  {
    "id": 21,
    "name": "JAYASRI SHANMATHI V",
    "github_link": "https://github.com/Jayasri-Shanmathi",
    "handles": {
      "leetcode": "Jayasri_shanmathi",
      "atcoder": "Jayasri18",
      "codeforces": "jayasrishanmathi",
      "hackerrank": "jayasrishanmathi",
      "github": "Jayasri-Shanmathi",
      "skillrack": "Jayasri_shanmathi"
    }
  },
  {
    "id": 22,
    "name": "VIJAYASRI S",
    "github_link": "https://github.com/Vijayasri-S",
    "handles": {
      "leetcode": "",
      "atcoder": "",
      "codeforces": "",
      "hackerrank": "",
      "github": "",
      "skillrack": "vijayasris"
    }
  },
  {
    "id": 23,
    "name": "JERUSLIN VINCE V",
    "github_link": "https://github.com/JERUSLIN-VINCE",
    "handles": {
      "leetcode": "Jeruslinvince",
      "atcoder": "Jeruslinvince",
      "codeforces": "jeruslin_vince",
      "hackerrank": "jeruslinvince",
      "github": "JERUSLIN-VINCE",
      "skillrack": "Jeruslinvince"
    }
  },
  {
    "id": 24,
    "name": "SAUMYA PETHUSAMY",
    "github_link": "https://github.com/saumya-1708",
    "handles": {
      "leetcode": "Saumya_1708",
      "atcoder": "saumya_1708",
      "codeforces": "Saumya1708",
      "hackerrank": "",
      "github": "saumya-1708",
      "skillrack": "Saumya_1708"
    }
  },
  {
    "id": 25,
    "name": "SURENDHIR V",
    "github_link": "https://github.com/Surendhirsurya",
    "handles": {
      "leetcode": "surendhirsurya",
      "atcoder": "Surendhir",
      "codeforces": "surendhir193",
      "hackerrank": "surendhir193",
      "github": "Surendhirsurya",
      "skillrack": "surendhirsurya"
    }
  },
  {
    "id": 26,
    "name": "SUJITH VARSHAN S",
    "github_link": "https://github.com/Sujith280705",
    "handles": {
      "leetcode": "Sujith_Varshan",
      "atcoder": "Sujith_Varshan",
      "codeforces": "sujithvarshan28",
      "hackerrank": "thundersujith07",
      "github": "Sujith280705",
      "skillrack": "Sujith_Varshan"
    }
  },
  {
    "id": 27,
    "name": "AADHI VALASU ARUN",
    "github_link": "https://github.com/Aadhi2121",
    "handles": {
      "leetcode": "Aadhi_Arun",
      "atcoder": "AadhiArun",
      "codeforces": "aadhiarun",
      "hackerrank": "aadhiarun",
      "github": "Aadhi2121",
      "skillrack": "Aadhi_Arun"
    }
  },
  {
    "id": 28,
    "name": "SETHURAM KARTHIKEYAN",
    "github_link": "https://github.com/sethuramkarthikeyan01-ops",
    "handles": {
      "leetcode": "Sethuram_06",
      "atcoder": "Sethuram",
      "codeforces": "SETHURAM_KARTHIKEYAN",
      "hackerrank": "",
      "github": "sethuramkarthikeyan01-ops",
      "skillrack": "Sethuram_06"
    }
  },
  {
    "id": 29,
    "name": "ANUBAMA I",
    "github_link": "https://github.com/Acesohappy",
    "handles": {
      "leetcode": "anubama2006",
      "atcoder": "Anubama",
      "codeforces": "TheGreatGatsby_9122",
      "hackerrank": "anubama2006",
      "github": "Acesohappy",
      "skillrack": "anubama2006"
    }
  },
  {
    "id": 30,
    "name": "SANTHOSH SHARAN B",
    "github_link": "https://github.com/sandynaukar",
    "handles": {
      "leetcode": "santhosh_sharan",
      "atcoder": "sandy_naukar",
      "codeforces": "santhoshsharanb",
      "hackerrank": "sandynaukar158",
      "github": "sandynaukar",
      "skillrack": "santhosh_sharan"
    }
  },
  {
    "id": 31,
    "name": "GOKILA HARINI S",
    "github_link": "https://github.com/gokilaharini/",
    "handles": {
      "leetcode": "Gokilaharini27",
      "atcoder": "Gokila_Harini",
      "codeforces": "gokila_harini_27",
      "hackerrank": "gokilaharini2795",
      "github": "gokilaharini",
      "skillrack": "Gokilaharini27"
    }
  },
  {
    "id": 32,
    "name": "ABISHEK J",
    "github_link": "https://github.com/MLAbishek",
    "handles": {
      "leetcode": "connectabishek",
      "atcoder": "Abishekj",
      "codeforces": "Abishek_J",
      "hackerrank": "connectabishek",
      "github": "MLAbishek",
      "skillrack": "connectabishek"
    }
  },
  {
    "id": 33,
    "name": "DURKESH P",
    "github_link": "https://github.com/durkesh-datasci",
    "handles": {
      "leetcode": "durkesh_p",
      "atcoder": "Durkesh",
      "codeforces": "Durkesh-data_sci",
      "hackerrank": "durkesh_00",
      "github": "durkesh-datasci",
      "skillrack": "durkesh_p"
    }
  },
  {
    "id": 34,
    "name": "SRIVARSHINI P",
    "github_link": "https://github.com/srivarshini-05",
    "handles": {
      "leetcode": "Srivarshini005",
      "atcoder": "Sri_005",
      "codeforces": "sri_005",
      "hackerrank": "psrivarshini80",
      "github": "srivarshini-05",
      "skillrack": "Srivarshini005"
    }
  },
  {
    "id": 35,
    "name": "DINESH BABU H",
    "github_link": "https://github.com/dineshbabu320",
    "handles": {
      "leetcode": "dineshbabu320",
      "atcoder": "hvdineshbabu",
      "codeforces": "hvdineshbabu",
      "hackerrank": "hvdineshbabu",
      "github": "dineshbabu320",
      "skillrack": "dineshbabu320"
    }
  },
  {
    "id": 36,
    "name": "DEEPIKA SHWETHA S",
    "github_link": "https://github.com/coder123-code",
    "handles": {
      "leetcode": "user8065tb",
      "atcoder": "",
      "codeforces": "deepikashwetha.sg",
      "hackerrank": "deepikashwetha_1",
      "github": "coder123-code",
      "skillrack": "user8065tb"
    }
  },
  {
    "id": 37,
    "name": "NISHANTHINI T",
    "github_link": "https://github.com/nishanthini5032-maker",
    "handles": {
      "leetcode": "Nishanthini2",
      "atcoder": "Nisha2",
      "codeforces": "",
      "hackerrank": "",
      "github": "nishanthini5032-maker",
      "skillrack": "Nishanthini2"
    }
  },
  {
    "id": 38,
    "name": "AKSHITHA GANDHI SANKARANARAYANAN",
    "github_link": "https://github.com/Akshitha1808",
    "handles": {
      "leetcode": "user3882pl",
      "atcoder": "Akshitha_S18",
      "codeforces": "Akshitha_S",
      "hackerrank": "akshitha_chithra",
      "github": "Akshitha1808",
      "skillrack": "user3882pl"
    }
  },
  {
    "id": 39,
    "name": "PARTHA SHARATHY K",
    "github_link": "https://github.com/Partha-Sharathy-K",
    "handles": {
      "leetcode": "Partha_Sharathy_K",
      "atcoder": "ParthaSharathy",
      "codeforces": "parthasharathy44",
      "hackerrank": "parthasharathy44",
      "github": "Partha-Sharathy-K",
      "skillrack": "Partha_Sharathy_K"
    }
  },
  {
    "id": 40,
    "name": "SHOBIKA D",
    "github_link": "https://github.com/nan",
    "handles": {
      "leetcode": "shobikadayanidhi",
      "atcoder": "shobikadayanidi",
      "codeforces": "",
      "hackerrank": "",
      "github": "",
      "skillrack": "shobikadayanidhi"
    }
  },
  {
    "id": 41,
    "name": "YUTHISHTRA BOSE M N",
    "github_link": "https://github.com/nan",
    "handles": {
      "leetcode": "yuthishtra_bose",
      "atcoder": "Yuthishtra_Bose",
      "codeforces": "M_N_YUTHISHTRA_BOSE",
      "hackerrank": "mnyuthishtrabose",
      "github": "",
      "skillrack": "yuthishtra_bose"
    }
  },
  {
    "id": 42,
    "name": "FANNY JOSE J",
    "github_link": "https://github.com/fannyjos",
    "handles": {
      "leetcode": "fanny_jose",
      "atcoder": "fanny_jose",
      "codeforces": "fannyjose004",
      "hackerrank": "fannyjose004",
      "github": "fannyjos",
      "skillrack": "fanny_jose"
    }
  },
  {
    "id": 43,
    "name": "MONIKA B",
    "github_link": "https://github.com/monikabaabu",
    "handles": {
      "leetcode": "monikabaabu",
      "atcoder": "monikabaabu",
      "codeforces": "monikabaabu",
      "hackerrank": "monikababu207",
      "github": "monikabaabu",
      "skillrack": "monikabaabu"
    }
  },
  {
    "id": 44,
    "name": "RISHWANTTHI R",
    "github_link": "https://github.com/Rishwantthi",
    "handles": {
      "leetcode": "Rishwantthi",
      "atcoder": "Rishwantthi2111",
      "codeforces": "rishwantthi18",
      "hackerrank": "rishwantthi18",
      "github": "Rishwantthi",
      "skillrack": "Rishwantthi"
    }
  },
  {
    "id": 45,
    "name": "RISHON JOS ANTON S",
    "github_link": "https://github.com/RishonAnton",
    "handles": {
      "leetcode": "RishonAnton",
      "atcoder": "rishonanton",
      "codeforces": "",
      "hackerrank": "",
      "github": "RishonAnton",
      "skillrack": "RishonAnton"
    }
  },
  {
    "id": 46,
    "name": "SHAKUNTH S",
    "github_link": "https://github.com/Master5401",
    "handles": {
      "leetcode": "Shakunth_Srinivasan",
      "atcoder": "5401_atcode",
      "codeforces": "5401thecoder",
      "hackerrank": "",
      "github": "Master5401",
      "skillrack": "Shakunth_Srinivasan"
    }
  },
  {
    "id": 47,
    "name": "PRAKASH M S",
    "github_link": "https://github.com/Prakash-M-S",
    "handles": {
      "leetcode": "Prakash9545",
      "atcoder": "",
      "codeforces": "prakashsaravanan9545",
      "hackerrank": "prakashsaravana6",
      "github": "Prakash-M-S",
      "skillrack": "Prakash9545"
    }
  },
  {
    "id": 48,
    "name": "MADHAVAN P",
    "github_link": "https://github.com/Madhavan1302",
    "handles": {
      "leetcode": "madhavan0823",
      "atcoder": "Madhavan13",
      "codeforces": "madhavan0923",
      "hackerrank": "madhavan0923",
      "github": "Madhavan1302",
      "skillrack": "madhavan0823"
    }
  },
  {
    "id": 49,
    "name": "SHIVESH ELANGOVAN",
    "github_link": "https://github.com/elite1238",
    "handles": {
      "leetcode": "Shivesh_E",
      "atcoder": "ShiveshE",
      "codeforces": "shiveshe",
      "hackerrank": "elangoshivesh",
      "github": "elite1238",
      "skillrack": "Shivesh_E"
    }
  },
  {
    "id": 50,
    "name": "SENTHILNATHAN D",
    "github_link": "https://github.com/senthilnathand",
    "handles": {
      "leetcode": "senthilnathandhanabalan86",
      "atcoder": "Senthilnathan",
      "codeforces": "SENTHILNATHAN.DHANABALAN",
      "hackerrank": "senthilnathandh1",
      "github": "senthilnathand",
      "skillrack": "senthilnathandhanabalan86"
    }
  },
  {
    "id": 51,
    "name": "RAJAN B",
    "github_link": "https://github.com/rajanbalaji",
    "handles": {
      "leetcode": "rajanbalaji",
      "atcoder": "rajan2005",
      "codeforces": "rajanbalaji05",
      "hackerrank": "",
      "github": "rajanbalaji",
      "skillrack": "rajanbalaji"
    }
  },
  {
    "id": 52,
    "name": "VISHVESH ROSHAN S",
    "github_link": "https://github.com/VishveshRoshan",
    "handles": {
      "leetcode": "Vishvesh31",
      "atcoder": "Vishvesh31",
      "codeforces": "Vishvesh31",
      "hackerrank": "",
      "github": "VishveshRoshan",
      "skillrack": "Vishvesh31"
    }
  },
  {
    "id": 53,
    "name": "MAHESHWARAN B",
    "github_link": "https://github.com/Mahes2112",
    "handles": {
      "leetcode": "maheshwaran-21",
      "atcoder": "Mahesh_2112",
      "codeforces": "mahesh_2112",
      "hackerrank": "mahesh07454964",
      "github": "Mahes2112",
      "skillrack": "maheshwaran-21"
    }
  },
  {
    "id": 54,
    "name": "SHIVASREETHA S",
    "github_link": "https://github.com/ShivasreethaS",
    "handles": {
      "leetcode": "UinJkZvtvm",
      "atcoder": "ShivasreethaS",
      "codeforces": "Shivasreetha",
      "hackerrank": "sshivasreetha",
      "github": "ShivasreethaS",
      "skillrack": "UinJkZvtvm"
    }
  },
  {
    "id": 55,
    "name": "PREETHI S",
    "github_link": "https://github.com/Preethi303",
    "handles": {
      "leetcode": "PreethiS_1",
      "atcoder": "PreethiS",
      "codeforces": "preethipos",
      "hackerrank": "spreethipos",
      "github": "Preethi303",
      "skillrack": "PreethiS_1"
    }
  },
  {
    "id": 56,
    "name": "MOGANA KRISHNA RAJASEKARAN",
    "github_link": "https://github.com/MOGANAKRISHNA-R",
    "handles": {
      "leetcode": "MoganKrishna_R",
      "atcoder": "MOGANA_KRISHNA",
      "codeforces": "moganakrishna4",
      "hackerrank": "moganakrishna43",
      "github": "MOGANAKRISHNA-R",
      "skillrack": "MoganKrishna_R"
    }
  },
  {
    "id": 57,
    "name": "SRI VARSHINI A",
    "github_link": "https://github.com/Sri-Varshini-A",
    "handles": {
      "leetcode": "Sri_Varshini_A",
      "atcoder": "Sri_Varshini_A",
      "codeforces": "Sri_Varshini_A",
      "hackerrank": "srivarshinianan1",
      "github": "Sri-Varshini-A",
      "skillrack": "Sri_Varshini_A"
    }
  },
  {
    "id": 58,
    "name": "HARESH SELVARAJ",
    "github_link": "https://github.com/HareshSelvaraj (Haresh Selvaraj)",
    "handles": {
      "leetcode": "",
      "atcoder": "",
      "codeforces": "Haresh_1305",
      "hackerrank": "hareshswork",
      "github": "",
      "skillrack": "hareshselvaraj"
    }
  },
  {
    "id": 59,
    "name": "NAVEEN RAJ A",
    "github_link": "https://github.com/naveenraj-245",
    "handles": {
      "leetcode": "naveenraj-245",
      "atcoder": "naveenraj245",
      "codeforces": "",
      "hackerrank": "",
      "github": "naveenraj-245",
      "skillrack": "naveenraj-245"
    }
  },
  {
    "id": 60,
    "name": "SUCHIR S M",
    "github_link": "https://github.com/SuchirSM",
    "handles": {
      "leetcode": "suchir25688618",
      "atcoder": "KmwKR9DM7VUZnf9HQ",
      "codeforces": "",
      "hackerrank": "",
      "github": "SuchirSM",
      "skillrack": "suchir25688618"
    }
  },
  {
    "id": 61,
    "name": "MOHAMMED FAIZ Y",
    "github_link": "https://github.com/FAIZ1409",
    "handles": {
      "leetcode": "Mohammed_Faiz",
      "atcoder": "Mohammed_Faiz",
      "codeforces": "Faizhere",
      "hackerrank": "faizacct",
      "github": "FAIZ1409",
      "skillrack": "Mohammed_Faiz"
    }
  },
  {
    "id": 62,
    "name": "JOLIYA D",
    "github_link": "https://github.com/JoliyaD",
    "handles": {
      "leetcode": "joliya",
      "atcoder": "joliya_2828",
      "codeforces": "joliya_28",
      "hackerrank": "",
      "github": "JoliyaD",
      "skillrack": "joliya"
    }
  },
  {
    "id": 63,
    "name": "AJAY RAMASAMY J",
    "github_link": "https://github.com/ajay-ramasamy",
    "handles": {
      "leetcode": "ajayram25",
      "atcoder": "ajayJ",
      "codeforces": "AjayRamasamyJ",
      "hackerrank": "ajay11220051",
      "github": "ajay-ramasamy",
      "skillrack": "ajayram25"
    }
  },
  {
    "id": 64,
    "name": "VISHWA R",
    "github_link": "https://github.com/vishwa206",
    "handles": {
      "leetcode": "vishwa_r21",
      "atcoder": "vishwa_r201",
      "codeforces": "Vishwa-21",
      "hackerrank": "vishwa_r21",
      "github": "vishwa206",
      "skillrack": "vishwa_r21"
    }
  },
  {
    "id": 65,
    "name": "CHERLENE A",
    "github_link": "https://github.com/Cherlene-A",
    "handles": {
      "leetcode": "Cherlene",
      "atcoder": "cherlene",
      "codeforces": "cherlene",
      "hackerrank": "cherlene0506",
      "github": "Cherlene-A",
      "skillrack": "Cherlene"
    }
  },
  {
    "id": 66,
    "name": "NANDHIKA A",
    "github_link": "https://github.com/nandhika66",
    "handles": {
      "leetcode": "nandhika66",
      "atcoder": "nandhika",
      "codeforces": "nandhika66",
      "hackerrank": "nandhika66",
      "github": "nandhika66",
      "skillrack": "nandhika66"
    }
  },
  {
    "id": 67,
    "name": "KOKILA C",
    "github_link": "https://github.com/KokilaChella",
    "handles": {
      "leetcode": "kokila_chella",
      "atcoder": "kokilachella",
      "codeforces": "kokila_chella",
      "hackerrank": "kokilachella23",
      "github": "KokilaChella",
      "skillrack": "kokila_chella"
    }
  },
  {
    "id": 68,
    "name": "SANJAI M",
    "github_link": "https://github.com/sanjai.github",
    "handles": {
      "leetcode": "sanjaim2005",
      "atcoder": "",
      "codeforces": "SanjaiM10",
      "hackerrank": "msanjai1012",
      "github": "",
      "skillrack": "sanjaim2005"
    }
  },
  {
    "id": 69,
    "name": "VISHNU PRASATH S B",
    "github_link": "https://github.com/Vishnuprasath1512",
    "handles": {
      "leetcode": "SBVishnuprasath",
      "atcoder": "",
      "codeforces": "Vishnuprasath",
      "hackerrank": "",
      "github": "Vishnuprasath1512",
      "skillrack": "SBVishnuprasath"
    }
  },
  {
    "id": 70,
    "name": "SIVA KUMAR M",
    "github_link": "https://github.com/sivakumar5757",
    "handles": {
      "leetcode": "sivakumar07",
      "atcoder": "sivakumar7",
      "codeforces": "sivakumar7",
      "hackerrank": "sivakumar120956",
      "github": "sivakumar5757",
      "skillrack": "sivakumar07"
    }
  },
  {
    "id": 71,
    "name": "GEETHIKA SHREE R",
    "github_link": "https://github.com/Geethika009",
    "handles": {
      "leetcode": "geethii",
      "atcoder": "geethi009",
      "codeforces": "",
      "hackerrank": "",
      "github": "Geethika009",
      "skillrack": "geethii"
    }
  },
  {
    "id": 72,
    "name": "TRYPHENA R",
    "github_link": "https://github.com/Tryphena-R",
    "handles": {
      "leetcode": "Tryphena_14",
      "atcoder": "tryphena",
      "codeforces": "tryphe",
      "hackerrank": "tryphenareuban",
      "github": "Tryphena-R",
      "skillrack": "Tryphena_14"
    }
  },
  {
    "id": 73,
    "name": "KISHOR N",
    "github_link": "https://github.com/Kishor-456",
    "handles": {
      "leetcode": "kishornagarajan",
      "atcoder": "KishorNagarajan",
      "codeforces": "Kishor_Nagarajan",
      "hackerrank": "",
      "github": "Kishor-456",
      "skillrack": "kishornagarajan"
    }
  },
  {
    "id": 74,
    "name": "SRI RAAGAV RATHNAM K",
    "github_link": "https://github.com/sriraagav05",
    "handles": {
      "leetcode": "sriraagav05",
      "atcoder": "sriraagav05",
      "codeforces": "sriraagav05",
      "hackerrank": "sriraagav05",
      "github": "sriraagav05",
      "skillrack": "sriraagav05"
    }
  },
  {
    "id": 75,
    "name": "HITESH KUMAR S",
    "github_link": "https://github.com/Hitesh-Kumar-S",
    "handles": {
      "leetcode": "SHK_2006",
      "atcoder": "",
      "codeforces": "hiteshkumarsrinivasan",
      "hackerrank": "hitesh_kumar_s",
      "github": "Hitesh-Kumar-S",
      "skillrack": "SHK_2006"
    }
  },
  {
    "id": 76,
    "name": "TREASA JOSEPH",
    "github_link": "https://github.com/TreasaJoseph105",
    "handles": {
      "leetcode": "Treasa_joseph",
      "atcoder": "Treasa_Joseph",
      "codeforces": "treasa7966",
      "hackerrank": "treajo7966",
      "github": "TreasaJoseph105",
      "skillrack": "Treasa_joseph"
    }
  },
  {
    "id": 77,
    "name": "AALIYA SHIFANA J",
    "github_link": "https://github.com/AaliyaJK",
    "handles": {
      "leetcode": "AaliyaShifanaJ",
      "atcoder": "AaliyaShifanaJ",
      "codeforces": "",
      "hackerrank": "",
      "github": "AaliyaJK",
      "skillrack": "AaliyaShifanaJ"
    }
  },
  {
    "id": 78,
    "name": "DALIYA D",
    "github_link": "https://github.com/Daliya28",
    "handles": {
      "leetcode": "Daliya_28",
      "atcoder": "Daliya28",
      "codeforces": "Daliya28",
      "hackerrank": "daliyadevadas",

      "github": "Daliya28",
      "skillrack": "Daliya_28"
    }
  },
  {
    "id": 79,
    "name": "MARIA CAMRYN A",
    "github_link": "https://github.com/MariaCamryn",
    "handles": {
      "leetcode": "xZz3jafbuH",
      "atcoder": "camy1415",
      "codeforces": "amariacamryn",
      "hackerrank": "amariacamryn",
      "github": "MariaCamryn",
      "skillrack": "xZz3jafbuH"
    }
  },
  {
    "id": 80,
    "name": "LOHITHADEVI M",
    "github_link": "https://github.com/Lohithadevi",
    "handles": {
      "leetcode":"LOHITHADEVI",
      "atcoder":"lohithadevi",
      "codeforces":"lohithadevi",
      "hackerrank": "",
      "github":"Lohithadevi",
      "skillrack": {
        "username": "LOHITHADEVI",
        "id": "449592",
        "key": "26c91b34db09ebec3d12b2994b0314caf130c192"
      }
    }
  },
  {
    "id": 81,
    "name": "YESWANTH RAJA G",
    "github_link": "https://github.com/yeswanth-ares",
    "handles": {
      "leetcode": "Yeswanth_Ares",
      "atcoder": "yeswanth_",
      "codeforces": "yeswanthraja79",
      "hackerrank": "yeswanthraja79",
      "github": "yeswanth-ares",
      "skillrack": "Yeswanth_Ares"
    }
  },
  {
    "id": 82,
    "name": "MADHUMITHA A H",
    "github_link": "https://github.com/MadhumithaAH",
    "handles": {
      "leetcode": "MadhumithaAH",
      "atcoder": "MadhumithaAH",
      "codeforces": "MadhumithaAH",
      "hackerrank": "madhuhari014",
      "github": "MadhumithaAH",
      "skillrack": "MadhumithaAH"
    }
  },
  {
    "id": 83,
    "name": "REYODIN IMMANUEL G",
    "github_link": "https://github.com/Reyodin-06",
    "handles": {
      "leetcode": "reyodin",
      "atcoder": "Reyodin006",
      "codeforces": "reyodin006",
      "hackerrank": "reyodin006",
      "github": "Reyodin-06",
      "skillrack": "reyodin"
    }
  },
  {
    "id": 84,
    "name": "SWETHA V S",
    "github_link": "https://github.com/Swethavenkat-16",
    "handles": {
      "leetcode": "Swetha__venkat",
      "atcoder": "Swetha_venkat",
      "codeforces": "swetha_venkat",
      "hackerrank": "swethavenkat369",
      "github": "Swethavenkat-16",
      "skillrack": "Swetha__venkat"
    }
  },
  {
    "id": 85,
    "name": "DHARSSHNE R",
    "github_link": "https://github.com/dharsshne",
    "handles": {
      "leetcode": "Dharsshne",
      "atcoder": "Dharsshne",
      "codeforces": "",
      "hackerrank": "",
      "github": "dharsshne",
      "skillrack": "Dharsshne"
    }
  },
  {
    "id": 86,
    "name": "BHUVANESHWARI N",
    "github_link": "https://github.com/Bhuvaneshwari-Narayanasamy",
    "handles": {
      "leetcode": "bhuvi_23",
      "atcoder": "",
      "codeforces": "Bhuvi__23",
      "hackerrank": "bhuvanaboo_2307",
      "github": "Bhuvaneshwari-Narayanasamy",
      "skillrack": "bhuvi_23"
    }
  },
  {
    "id": 87,
    "name": "DIVYADHARSHINI A",
    "github_link": "https://github.com/Divya-9125",
    "handles": {
      "leetcode": "diivyasri09122005",
      "atcoder": "divi9125",
      "codeforces": "Divya9125a",
      "hackerrank": "diivyasri0912201",
      "github": "Divya-9125",
      "skillrack": "diivyasri09122005"
    }
  },
  {
    "id": 88,
    "name": "SAMUEL ABISHEK R",
    "github_link": "https://github.com/SamuelAbishek",
    "handles": {
      "leetcode": "SamuelAbishek",
      "atcoder": "Samuel_Abishek_R",
      "codeforces": "Samuel_Abishek_R",
      "hackerrank": "samuelabishek181",
      "github": "SamuelAbishek",
      "skillrack": "SamuelAbishek"
    }
  },
  {
    "id": 89,
    "name": "KARAN PAUL M",
    "github_link": "https://github.com/Challenger-0474",
    "handles": {
      "leetcode": "karan__11",
      "atcoder": "Karan_0425",
      "codeforces": "karanzworkflow",
      "hackerrank": "karanzworkflow",
      "github": "Challenger-0474",
      "skillrack": "karan__11"
    }
  },
  {
    "id": 90,
    "name": "ASHWATH R",
    "github_link": "https://github.com/ashwath1729/Ashwath",
    "handles": {
      "leetcode": "AshwathRajasekaran",
      "atcoder": "ashwathr1729",
      "codeforces": "",
      "hackerrank": "",
      "github": "",
      "skillrack": "AshwathRajasekaran"
    }
  },
  {
    "id": 91,
    "name": "YOGESH KANNA R",
    "github_link": "https://github.com/YogeshKanna1206",
    "handles": {
      "leetcode": "Yogesh_Kanna",
      "atcoder": "yogeshkanna120",
      "codeforces": "yogeshkanna1206",
      "hackerrank": "yogeshkanna1206",
      "github": "YogeshKanna1206",
      "skillrack": "Yogesh_Kanna"
    }
  },
  {
    "id": 92,
    "name": "HARI PRASATH MANI S",
    "github_link": "https://github.com/Hariprasathmani",
    "handles": {
      "leetcode": "Hariprasathmani",
      "atcoder": "hariprasath102",
      "codeforces": "hariprasathmani102",
      "hackerrank": "hariprasathmani5",
      "github": "Hariprasathmani",
      "skillrack": "Hariprasathmani"
    }
  },
  {
    "id": 93,
    "name": "KALAIYARASAN P",
    "github_link": "https://github.com/Kalaiyarasanpushparaj",
    "handles": {
      "leetcode": "kalaiyarasan18",
      "atcoder": "KALAIYARASAN",
      "codeforces": "kalai162617",
      "hackerrank": "kalai162617",
      "github": "Kalaiyarasanpushparaj",
      "skillrack": "kalaiyarasan18"
    }
  },
  {
    "id": 94,
    "name": "PRESHNEV R",
    "github_link": "https://github.com/nan",
    "handles": {
      "leetcode": "preshnevr",
      "atcoder": "preshnevr",
      "codeforces": "",
      "hackerrank": "",
      "github": "",
      "skillrack": "preshnevr"
    }
  },
  {
    "id": 95,
    "name": "RANJITH R",
    "github_link": "https://github.com/Ranjith00005",
    "handles": {
      "leetcode": "Ranjith00005",
      "atcoder": "ranjith_05",
      "codeforces": "ranjithsme1",
      "hackerrank": "ranjithsme1",
      "github": "Ranjith00005",
      "skillrack": "Ranjith00005"
    }
  },
  {
    "id": 96,
    "name": "RISHIESHWARI S",
    "github_link": "https://github.com/RishieshwariS",
    "handles": {
      "leetcode": "Rishieshwari",
      "atcoder": "RishieshwariS",
      "codeforces": "",
      "hackerrank": "",
      "github": "RishieshwariS",
      "skillrack": "Rishieshwari"
    }
  },
  {
    "id": 97,
    "name": "HARITA M U",
    "github_link": "https://github.com/Harita27/Rock-Fall-Prediction",
    "handles": {
      "leetcode": "haritamu27",
      "atcoder": "harita27",
      "codeforces": "Harita27",
      "hackerrank": "",
      "github": "",
      "skillrack": "haritamu27"
    }
  },
  {
    "id": 98,
    "name": "KRISHNA K",
    "github_link": "https://github.com/ml-krishna-k",
    "handles": {
      "leetcode": "Krishnaraj_k",
      "atcoder": "Krishna05",
      "codeforces": "krishnaraj-k",
      "hackerrank": "kkrishnarajr",
      "github": "ml-krishna-k",
      "skillrack": "Krishnaraj_k"
    }
  },
  {
    "id": 99,
    "name": "KATHRESHA BESTINA B",
    "github_link": "https://github.com/KathreshaBestinaB",
    "handles": {
      "leetcode": "WYBJ9iu80v",
      "atcoder": "Kath_05",
      "codeforces": "Kathresha",
      "hackerrank": "Kathreshabestina",
      "github": "KathreshaBestinaB",
      "skillrack": "WYBJ9iu80v"
    }
  },
  {
    "id": 100,
    "name": "SAI SIVA RUBHA H",
    "github_link": "https://github.com/SaiSivaRubha",
    "handles": {
      "leetcode": "SaiSivaRubha30",
      "atcoder": "saisivarubha",
      "codeforces": "saisivarubha123",
      "hackerrank": "saisivarubhakh",
      "github": "SaiSivaRubha",
      "skillrack": "SaiSivaRubha30"
    }
  },
  {
    "id": 101,
    "name": "SRIVARSAN J P",
    "github_link": "https://github.com/SRIVARSAN1012",
    "handles": {
      "leetcode": "srivarsanjp",
      "atcoder": "Srivarsan",
      "codeforces": "srivarsanjpxa",
      "hackerrank": "srivarsanjpxa",
      "github": "SRIVARSAN1012",
      "skillrack": "srivarsanjp"
    }
  },
  {
    "id": 102,
    "name": "KOVENDAN R",
    "github_link": "https://github.com/Kovendan-R",
    "handles": {
      "leetcode": "KovendanR",
      "atcoder": "KovendanR",
      "codeforces": "kovendan",
      "hackerrank": "kovendan18",
      "github": "Kovendan-R",
      "skillrack": "KovendanR"
    }
  },
  {
    "id": 103,
    "name": "VIGNESHKUMAR V",
    "github_link": "https://github.com/nan",
    "handles": {
      "leetcode": "vickyscorpz",
      "atcoder": "vigneshkumar",
      "codeforces": "",
      "hackerrank": "",
      "github": "",
      "skillrack": "vickyscorpz"
    }
  },
  {
    "id": 104,
    "name": "KESHAV SRINIVAS M",
    "github_link": "https://github.com/keshsrini",
    "handles": {
      "leetcode": "keshavsrini",
      "atcoder": "keshavsrini",
      "codeforces": "keshavsrini",
      "hackerrank": "keshavsrinivasm",
      "github": "keshsrini",
      "skillrack": "keshavsrini"
    }
  },
  {
    "id": 105,
    "name": "GOWRISHANKARI S",
    "github_link": "https://github.com/Shaxxshankari",
    "handles": {
      "leetcode": "Gowri_Shankari_S",
      "atcoder": "Gowrishankari_S",
      "codeforces": "gowrishankarigs15",
      "hackerrank": "gowrishankarigs1",
      "github": "Shaxxshankari",
      "skillrack": "Gowri_Shankari_S"
    }
  },
  {
    "id": 106,
    "name": "SAHAYA ANGEL S",
    "github_link": "https://github.com/SahayaAngelS",
    "handles": {
      "leetcode": "sahayaangel",
      "atcoder": "SahayaAngel",
      "codeforces": "sahayaAngel",
      "hackerrank": "",
      "github": "SahayaAngelS",
      "skillrack": "sahayaangel"
    }
  },
  {
    "id": 107,
    "name": "SRIRAM K",
    "github_link": "https://github.com/Sri-0105",
    "handles": {
      "leetcode": "Sriram0105",
      "atcoder": "Sriram0105",
      "codeforces": "Sriram0105",
      "hackerrank": "sriramkannan0105",
      "github": "Sri-0105",
      "skillrack": "Sriram0105"
    }
  },
  {
    "id": 108,
    "name": "ASHWINI R",
    "github_link": "https://github.com/Ashwini-R29",
    "handles": {
      "leetcode": "Ashwini-R",
      "atcoder": "Ashwini_R",
      "codeforces": "Ashwini-R",
      "hackerrank": "ashwiniravi29201",
      "github": "Ashwini-R29",
      "skillrack": "Ashwini-R"
    }
  },
  {
    "id": 109,
    "name": "MITHRA J",
    "github_link": "https://github.com/Mithra-J",
    "handles": {
      "leetcode": "mithraacct",
      "atcoder": "Mithraj",
      "codeforces": "mithraacct",
      "hackerrank": "mithraacct",
      "github": "Mithra-J",
      "skillrack": "mithraacct"
    }
  },
  {
    "id": 110,
    "name": "MEENACHI SUNDARESAN J",
    "github_link": "https://github.com/jms-luck",
    "handles": {
      "leetcode": "jms_luck",
      "atcoder": "jms_luck",
      "codeforces": "jms-luck",
      "hackerrank": "meenachisundare1",
      "github": "jms-luck",
      "skillrack": "jms_luck"
    }
  },
  {
    "id": 111,
    "name": "GIRI S",
    "github_link": "https://github.com/girisankaran",
    "handles": {
      "leetcode": "ugfCmTkMpb",
      "atcoder": "GIRIS",
      "codeforces": "girisankaran1973",
      "hackerrank": "girisankaran1973",
      "github": "girisankaran",
      "skillrack": "ugfCmTkMpb"
    }
  },
  {
    "id": 112,
    "name": "NIGITHA B",
    "github_link": "https://github.com/Nigitha02",
    "handles": {
      "leetcode": "Nigithabala",
      "atcoder": "Nigitha",
      "codeforces": "nigitha",
      "hackerrank": "nigitha05",
      "github": "Nigitha02",
      "skillrack": "Nigithabala"
    }
  },
  {
    "id": 113,
    "name": "PRANAV ARYA R S",
    "github_link": "https://github.com/Arya101005",
    "handles": {
      "leetcode": "PranavAryaRS",
      "atcoder": "PranavArya",
      "codeforces": "pranavarya2005",
      "hackerrank": "",
      "github": "Arya101005",
      "skillrack": "PranavAryaRS"
    }
  },
  {
    "id": 114,
    "name": "PRAKRITI P",
    "github_link": "https://github.com/Prakriti03340",
    "handles": {
      "leetcode": "Prakritipraba",
      "atcoder": "Prakriti_P",
      "codeforces": "",
      "hackerrank": "",
      "github": "Prakriti03340",
      "skillrack": "Prakritipraba"
    }
  },
  {
    "id": 115,
    "name": "RESHMA S",
    "github_link": "https://github.com/Reshmasethuraman",
    "handles": {
      "leetcode": "",
      "atcoder": "",
      "codeforces": "",
      "hackerrank": "",
      "github": "",
      "skillrack": "reshmas"
    }
  },
  {
    "id": 116,
    "name": "ANCY ANTONY  A  L",
    "github_link": "https://github.com/ancy3115",
    "handles": {
      "leetcode": "ancy_antony",
      "atcoder": "ancy26",
      "codeforces": "ancy26",
      "hackerrank": "ancyantony26",
      "github": "ancy3115",
      "skillrack": "ancy_antony"
    }
  },
  {
    "id": 117,
    "name": "DHIVYABHARATH P",
    "github_link": "https://github.com/dhivyabharath-30",
    "handles": {
      "leetcode": "dhivyabharath-30",
      "atcoder": "Dhivyabharath",
      "codeforces": "dhivyabharath",
      "hackerrank": "dhivyabharath201",
      "github": "dhivyabharath-30",
      "skillrack": "dhivyabharath-30"
    }
  },
  {
    "id": 118,
    "name": "SUJAN V",
    "github_link": "https://github.com/sujan58",
    "handles": {
      "leetcode": "Sujan_55",
      "atcoder": "sujan05",
      "codeforces": "sujan_05",
      "hackerrank": "sujan_3176_ads",
      "github": "sujan58",
      "skillrack": "Sujan_55"
    }
  },
  {
    "id": 119,
    "name": "JEROCIN ROYALGOLD M",
    "github_link": "https://github.com/JerocinRoyalgold",
    "handles": {
      "leetcode": "Jerocin_Royalgold_M",
      "atcoder": "JerocinRoyalGold",
      "codeforces": "jerocin2692005",
      "hackerrank": "Jerocin",
      "github": "JerocinRoyalgold",
      "skillrack": "Jerocin_Royalgold_M"
    }
  },
  {
    "id": 120,
    "name": "YUVAN SHANKAR G",
    "github_link": "https://github.com/YuvanShankar2006",
    "handles": {
      "leetcode": "yuvan_143_1",
      "atcoder": "yuvan02",
      "codeforces": "Yuvan_shankarg",
      "hackerrank": "Yuvanshankar3191",
      "github": "YuvanShankar2006",
      "skillrack": "yuvan_143_1"
    }
  },
  {
    "id": 121,
    "name": "AKASH M S",
    "github_link": "https://github.com/MS-AKASH-13",
    "handles": {
      "leetcode": "MSAkash",
      "atcoder": "",
      "codeforces": "",
      "hackerrank": "",
      "github": "MS-AKASH-13",
      "skillrack": "MSAkash"
    }
  },
  {
    "id": 122,
    "name": "ASWINI P",
    "github_link": "https://github.com/Aswini-P22",
    "handles": {
      "leetcode": "",
      "atcoder": "",
      "codeforces": "",
      "hackerrank": "",
      "github": "Aswini-P22",
      "skillrack": "aswinip"
    }
  },
  {
    "id": 123,
    "name": "RENISH SOUNDHRA S",
    "github_link": "https://github.com/Renish-Soundhra",
    "handles": {
      "leetcode": "RENISH_SOUNDHRA_S",
      "atcoder": "RenishSoundhra_S",
      "codeforces": "RenishSoundhra",
      "hackerrank": "renishsoundhra",
      "github": "Renish-Soundhra",
      "skillrack": "RENISH_SOUNDHRA_S"
    }
  },
  {
    "id": 124,
    "name": "SUMASHKRISHNA MARIYAPPAN",
    "github_link": "https://github.com/Sumash-Krishna",
    "handles": {
      "leetcode": "SumashKrishna",
      "atcoder": "SumashKrishna_M",
      "codeforces": "sumashxoffl",
      "hackerrank": "sumashoffl",
      "github": "Sumash-Krishna",
      "skillrack": "SumashKrishna"
    }
  },
  {
    "id": 125,
    "name": "RICHARD DANIEL J",
    "github_link": "https://github.com/RICHARD44720",
    "handles": {
      "leetcode": "Richard_JRD",
      "atcoder": "Richard__",
      "codeforces": "richard27.2005",
      "hackerrank": "richard27_2005",
      "github": "RICHARD44720",
      "skillrack": "Richard_JRD"
    }
  },
  {
    "id": 126,
    "name": "SIVAANI R P",
    "github_link": "https://github.com/sivushri-1128",
    "handles": {
      "leetcode": "sivaanirp2802",
      "atcoder": "Sivaavi",
      "codeforces": "sivaanikumar2802",
      "hackerrank": "23ee264",
      "github": "sivushri-1128",
      "skillrack": "sivaanirp2802"
    }
  },
  {
    "id": 127,
    "name": "LAKSHITHA R E",
    "github_link": "https://github.com/Lakshitha-R-E",
    "handles": {
      "leetcode": "Lakshitha_R_E",
      "atcoder": "Lakshitha_R_E",
      "codeforces": "Lakshitha_R_E",
      "hackerrank": "lakshitha_re",
      "github": "Lakshitha-R-E",
      "skillrack": "Lakshitha_R_E"
    }
  },
  {
    "id": 128,
    "name": "KANISHK K S",
    "github_link": "https://github.com/KANISHKGX",
    "handles": {
      "leetcode": "ftPFMlWMLL",
      "atcoder": "kanishkks",
      "codeforces": "KanishkKS",
      "hackerrank": "kani29august",
      "github": "KANISHKGX",
      "skillrack": "ftPFMlWMLL"
    }
  },
  {
    "id": 129,
    "name": "SHIFANA DAS C",
    "github_link": "https://github.com/Shifanadas",
    "handles": {
      "leetcode": "shifanadas",
      "atcoder": "shifanadas",
      "codeforces": "shifana_das2005",
      "hackerrank": "shifanadas2005",
      "github": "Shifanadas",
      "skillrack": "shifanadas"
    }
  },
  {
    "id": 130,
    "name": "DINESH G",
    "github_link": "https://github.com/Dinesh008-1",
    "handles": {
      "leetcode": "Y1TGEm90OL",
      "atcoder": "",
      "codeforces": "",
      "hackerrank": "",
      "github": "Dinesh008-1",
      "skillrack": "Y1TGEm90OL"
    }
  },
  {
    "id": 131,
    "name": "DEEOLIN R J",
    "github_link": "https://github.com/Deeolin",
    "handles": {
      "leetcode": "deeolinrjmtm",
      "atcoder": "Deeolin",
      "codeforces": "",
      "hackerrank": "",
      "github": "Deeolin",
      "skillrack": "deeolinrjmtm"
    }
  },
  {
    "id": 132,
    "name": "NITHEESH V",
    "github_link": "https://github.com/Nitheeshfanus",
    "handles": {
      "leetcode": "Nitheesh_V30",
      "atcoder": "",
      "codeforces": "NitheeshV",
      "hackerrank": "Nitheeshfanus",
      "github": "Nitheeshfanus",
      "skillrack": "Nitheesh_V30"
    }
  },
  {
    "id": 133,
    "name": "YASHAWINI CHANDRASEKAR",
    "github_link": "https://github.com/yashawinic",
    "handles": {
      "leetcode": "YashawiniChandrasekar",
      "atcoder": "Yashawini15",
      "codeforces": "yashawinic",
      "hackerrank": "",
      "github": "yashawinic",
      "skillrack": "YashawiniChandrasekar"
    }
  },
  {
    "id": 134,
    "name": "LINGESHWARAN K S",
    "github_link": "https://github.com/Lingeshwaran1312",
    "handles": {
      "leetcode": "sLKtyEE3Q2",
      "atcoder": "Lingeshwaran_KS",
      "codeforces": "",
      "hackerrank": "",
      "github": "Lingeshwaran1312",
      "skillrack": "sLKtyEE3Q2"
    }
  },
  {
    "id": 135,
    "name": "MOHAMED MARZUQ THARIF S",
    "github_link": "https://github.com/nan",
    "handles": {
      "leetcode": "",
      "atcoder": "",
      "codeforces": "",
      "hackerrank": "",
      "github": "",
      "skillrack": "mohamedmarzuqtharifs"
    }
  },
  {
    "id": 136,
    "name": "MUTHUKUMARASAMY M",
    "github_link": "https://github.com/Muthukumarasamy-techML",
    "handles": {
      "leetcode": "Muthushiva",
      "atcoder": "Muthukumarasamy",
      "codeforces": "MuthukumarasamyM",
      "hackerrank": "muthu61879",
      "github": "Muthukumarasamy-techML",
      "skillrack": "Muthushiva"
    }
  },
  {
    "id": 137,
    "name": "MANIKANDAN K",
    "github_link": "https://github.com/mm6597970",
    "handles": {
      "leetcode": "ManiKandan_k_25",
      "atcoder": "manikandan25",
      "codeforces": "",
      "hackerrank": "manikandan250720",
      "github": "mm6597970",
      "skillrack": "ManiKandan_k_25"
    }
  },
  {
    "id": 138,
    "name": "THAMIZHARASAN N",
    "github_link": "https://github.com/Thamizh-01 (Thamizh Arasan)",
    "handles": {
      "leetcode": "thamizhTK",
      "atcoder": "",
      "codeforces": "Thamizh01",
      "hackerrank": "",
      "github": "",
      "skillrack": "thamizhTK"
    }
  },
  {
    "id": 139,
    "name": "ARNESH R",
    "github_link": "https://github.com/Arnesh-26",
    "handles": {
      "leetcode": "JqKkRqCFx8",
      "atcoder": "",
      "codeforces": "rajarnesh49",
      "hackerrank": "rajarnesh49",
      "github": "Arnesh-26",
      "skillrack": "JqKkRqCFx8"
    }
  },
  {
    "id": 140,
    "name": "VISHNU PRASATH P",
    "github_link": "https://github.com/nan",
    "handles": {
      "leetcode": "Vishn_uh",
      "atcoder": "",
      "codeforces": "",
      "hackerrank": "",
      "github": "",
      "skillrack": "Vishn_uh"
    }
  },
  {
    "id": 141,
    "name": "SAM PUNITHA RAJ D",
    "github_link": "https://github.com/SamPunithaRajD",
    "handles": {
      "leetcode": "SamPunithaRajD",
      "atcoder": "SamPunithaRaj",
      "codeforces": "gamingwithsam978",
      "hackerrank": "gamingwithsam978",
      "github": "SamPunithaRajD",
      "skillrack": "SamPunithaRajD"
    }
  },
  {
    "id": 142,
    "name": "THARSAN KANTHASWAMY",
    "github_link": "https://github.com/TharsanKanthaswamy",
    "handles": {
      "leetcode": "sYHDaBrXQa",
      "atcoder": "Tharsan_",
      "codeforces": "WarDaddy8055",
      "hackerrank": "tharsank2",
      "github": "TharsanKanthaswamy",
      "skillrack": "sYHDaBrXQa"
    }
  },
  {
    "id": 143,
    "name": "MOHAMMED IBRAHIM J",
    "github_link": "https://github.com/MOHAMMED-IBRAHIM-J-312423104140",
    "handles": {
      "leetcode": "Mohammed_Ibrahim_J",
      "atcoder": "IBRAHIM_43",
      "codeforces": "",
      "hackerrank": "",
      "github": "MOHAMMED-IBRAHIM-J-312423104140",
      "skillrack": "Mohammed_Ibrahim_J"
    }
  },
  {
    "id": 144,
    "name": "SHYAM SUNDAR",
    "github_link": "https://github.com/Shyam0709",
    "handles": {
      "leetcode": "Shyam0709",
      "atcoder": "Shyam070905",
      "codeforces": "shyam0709",
      "hackerrank": "6152_SHYAMSUNDAR",
      "github": "Shyam0709",
      "skillrack": "Shyam0709"
    }
  },
  {
    "id": 145,
    "name": "JOSEPH SUNDAR MARSHAL F V",
    "github_link": "https://github.com/Joseph3331",
    "handles": {
      "leetcode": "",
      "atcoder": "Joseph3331",
      "codeforces": "Joseph3331",
      "hackerrank": "23it12011",
      "github": "Joseph3331",
      "skillrack": "josephsundarmarshalfv"
    }
  },
  {
    "id": 146,
    "name": "MARCUS FRANKLIN J",
    "github_link": "https://github.com/MarcusFranklin-GIT",
    "handles": {
      "leetcode": "MarcusFranklin",
      "atcoder": "Marcus_Franklin",
      "codeforces": "marcus.franklin.j12",
      "hackerrank": "marcus_franklin1",
      "github": "MarcusFranklin-GIT",
      "skillrack": "MarcusFranklin"
    }
  },
  {
    "id": 147,
    "name": "MOHAMED ARFAN S M",
    "github_link": "https://github.com/CatOn60Hz",
    "handles": {
      "leetcode": "smmohamedarfan",
      "atcoder": "Cat_On_165Hz",
      "codeforces": "smmohamedarfan",
      "hackerrank": "smmohamedarfan",
      "github": "CatOn60Hz",
      "skillrack": "smmohamedarfan"
    }
  },
  {
    "id": 148,
    "name": "NITISH M",
    "github_link": "https://github.com/DECAF222",
    "handles": {
      "leetcode": "Nitish_17_M",
      "atcoder": "Nitish_M",
      "codeforces": "",
      "hackerrank": "",
      "github": "DECAF222",
      "skillrack": "Nitish_17_M"
    }
  },
  {
    "id": 149,
    "name": "DINESH K",
    "github_link": "https://github.com/dinesh2432",
    "handles": {
      "leetcode": "DINESH__DK",
      "atcoder": "Dinesh0906",
      "codeforces": "ddk113311",
      "hackerrank": "",
      "github": "dinesh2432",
      "skillrack": "DINESH__DK"
    }
  },
  {
    "id": 150,
    "name": "MURJANAH SHAHUL HAMEED",
    "github_link": "https://github.com/murjanah-shahul (Murjanah Shahul Hameed)",
    "handles": {
      "leetcode": "murjanahshahul",
      "atcoder": "",
      "codeforces": "",
      "hackerrank": "",
      "github": "",
      "skillrack": "murjanahshahul"
    }
  },
  {
    "id": 151,
    "name": "SAI KARTHIK MURALIDHAR",
    "github_link": "https://github.com/nan",
    "handles": {
      "leetcode": "saikarthik1307",
      "atcoder": "",
      "codeforces": "",
      "hackerrank": "",
      "github": "",
      "skillrack": "saikarthik1307"
    }
  },
  {
    "id": 152,
    "name": "HAMUDUTHEEN S",
    "github_link": "https://github.com/HAMUDUTHEEN",
    "handles": {
      "leetcode": "hamudutheen",
      "atcoder": "hamudutheen",
      "codeforces": "",
      "hackerrank": "",
      "github": "HAMUDUTHEEN",
      "skillrack": "hamudutheen"
    }
  },
  {
    "id": 153,
    "name": "ABISHEIK P T",
    "github_link": "https://github.com/nan",
    "handles": {
      "leetcode": "abisheik05",
      "atcoder": "",
      "codeforces": "",
      "hackerrank": "",
      "github": "",
      "skillrack": "abisheik05"
    }
  },
  {
    "id": 154,
    "name": "SAHITI SURESH",
    "github_link": "https://github.com/Sahiti-Suresh",
    "handles": {
      "leetcode": "Sahiti_Suresh",
      "atcoder": "Sahiti_Suresh",
      "codeforces": "sahiti.s007",
      "hackerrank": "sahitisuresh321",
      "github": "Sahiti-Suresh",
      "skillrack": "Sahiti_Suresh"
    }
  },
  {
    "id": 155,
    "name": "AATHEESH GOKULA PRASATH V",
    "github_link": "https://github.com/AATHEESH007",
    "handles": {
      "leetcode": "aatheeshfrime",
      "atcoder": "Aatheesh",
      "codeforces": "Aatheesh",
      "hackerrank": "rsvbaskaran",
      "github": "AATHEESH007",
      "skillrack": "aatheeshfrime"
    }
  },
  {
    "id": 156,
    "name": "MOHAMED ASIF S M",
    "github_link": "https://github.com/Asar007",
    "handles": {
      "leetcode": "HALFAWAKENCATTO",
      "atcoder": "Asif_16",
      "codeforces": "",
      "hackerrank": "",
      "github": "Asar007",
      "skillrack": "HALFAWAKENCATTO"
    }
  },
  {
    "id": 157,
    "name": "SASTIDHARAN T",
    "github_link": "https://github.com/Sastidharan07",
    "handles": {
      "leetcode": "Sastidharan_07",
      "atcoder": "Sastidharan",
      "codeforces": "",
      "hackerrank": "sastidharan07",
      "github": "Sastidharan07",
      "skillrack": "Sastidharan_07"
    }
  },
  {
    "id": 158,
    "name": "MAHENDRA P",
    "github_link": "https://github.com/Mahendraxprasanna",
    "handles": {
      "leetcode": "mahendra_lmao",
      "atcoder": "Mahendra1",
      "codeforces": "mahendra232005",
      "hackerrank": "mahendra232005",
      "github": "Mahendraxprasanna",
      "skillrack": "mahendra_lmao"
    }
  },
  {
    "id": 159,
    "name": "NAREN KARTHIK SRINIVASAN",
    "github_link": "https://github.com/Nk-57",
    "handles": {
      "leetcode": "nk_57",
      "atcoder": "Naren_karthik",
      "codeforces": "nk_57",
      "hackerrank": "narenkarthiks107",
      "github": "Nk-57",
      "skillrack": "nk_57"
    }
  },
  {
    "id": 160,
    "name": "RENITA JASMINE T",
    "github_link": "https://github.com/Renita-jas",
    "handles": {
      "leetcode": "Renita_jasmine",
      "atcoder": "reni2006",
      "codeforces": "",
      "hackerrank": "",
      "github": "Renita-jas",
      "skillrack": "Renita_jasmine"
    }
  },
  {
    "id": 161,
    "name": "KARMUKILAN V",
    "github_link": "https://github.com/karmukilan2006",
    "handles": {
      "leetcode": "U5MHswi8ep",
      "atcoder": "karmukilanv",
      "codeforces": "karmukilanv33",
      "hackerrank": "karmukilanv33",
      "github": "karmukilan2006",
      "skillrack": "U5MHswi8ep"
    }
  },
  {
    "id": 162,
    "name": "SACHIN B",
    "github_link": "https://github.com/Sachin-sjit",
    "handles": {
      "leetcode": "_Sachin_B",
      "atcoder": "",
      "codeforces": "",
      "hackerrank": "",
      "github": "",
      "skillrack": "_Sachin_B"
    }
  },
  {
    "id": 163,
    "name": "ANEESA ZAINAB F",
    "github_link": "https://github.com/ffrazi",
    "handles": {
      "leetcode": "Aneesa_Zainab_F",
      "atcoder": "ffrazi",
      "codeforces": "Ffrazi",
      "hackerrank": "aneesazainabf",
      "github": "ffrazi",
      "skillrack": "Aneesa_Zainab_F"
    }
  },
  {
    "id": 164,
    "name": "SHARNISHA J",
    "github_link": "https://github.com/Sharnisha-J",
    "handles": {
      "leetcode": "nBfF3IJF1w",
      "atcoder": "Sharnisha",
      "codeforces": "",
      "hackerrank": "",
      "github": "Sharnisha-J",
      "skillrack": "nBfF3IJF1w"
    }
  },
  {
    "id": 165,
    "name": "SANDHIYA G",
    "github_link": "https://github.com/SandhiyaGY",
    "handles": {
      "leetcode": "sandhiya_gurumoorthy",
      "atcoder": "SandhiyaG",
      "codeforces": "sandhiyagy",
      "hackerrank": "s16261261",
      "github": "SandhiyaGY",
      "skillrack": "sandhiya_gurumoorthy"
    }
  },
  {
    "id": 166,
    "name": "SRINIVASAN S",
    "github_link": "https://github.com/Srinivasan-03",
    "handles": {
      "leetcode": "Srinivasan-S",
      "atcoder": "Cheenu03",
      "codeforces": "srinivasan_03",
      "hackerrank": "srinivasan_sjece",
      "github": "Srinivasan-03",
      "skillrack": "Srinivasan-S"
    }
  },
  {
    "id": 167,
    "name": "BARATHRAJ L",
    "github_link": "https://github.com/Barath-2006",
    "handles": {
      "leetcode": "barath2006",
      "atcoder": "barath2006",
      "codeforces": "lbarathraj2006",
      "hackerrank": "",
      "github": "Barath-2006",
      "skillrack": "barath2006"
    }
  },
  {
    "id": 168,
    "name": "MONISHA C",
    "github_link": "https://github.com/Monishaclement",
    "handles": {
      "leetcode": "Monisha-12",
      "atcoder": "Monisha12",
      "codeforces": "",
      "hackerrank": "",
      "github": "Monishaclement",
      "skillrack": "Monisha-12"
    }
  },
  {
    "id": 169,
    "name": "PARTHASARATHY S",
    "github_link": "https://github.com/nan",
    "handles": {
      "leetcode": "parthasarathy__s",
      "atcoder": "sarathy2005",
      "codeforces": "parthasarathy_27",
      "hackerrank": "sarathy73394521",
      "github": "",
      "skillrack": "parthasarathy__s"
    }
  },
  {
    "id": 170,
    "name": "SIVASURYAKANTH M",
    "github_link": "https://github.com/nan",
    "handles": {
      "leetcode": "SIVASURYAKANTH",
      "atcoder": "SIVASURYAKANTH",
      "codeforces": "",
      "hackerrank": "",
      "github": "",
      "skillrack": "SIVASURYAKANTH"
    }
  },
  {
    "id": 171,
    "name": "JOSEPH DANIEL",
    "github_link": "https://github.com/josephdaniel8805",
    "handles": {
      "leetcode": "JosephDaniel8805",
      "atcoder": "josephdaniel8805",
      "codeforces": "josephdaniel8805",
      "hackerrank": "josephdaniel8805",
      "github": "josephdaniel8805",
      "skillrack": "JosephDaniel8805"
    }
  },
  {
    "id": 172,
    "name": "SONICA VAZ J",
    "github_link": "https://github.com/Sonica-Vaz-J",
    "handles": {
      "leetcode": "sonica_vaz_j",
      "atcoder": "sonicavazj",
      "codeforces": "",
      "hackerrank": "",
      "github": "Sonica-Vaz-J",
      "skillrack": "sonica_vaz_j"
    }
  },
  {
    "id": 173,
    "name": "JAYAKRISHNAN S",
    "github_link": "https://github.com/jaikrishnan-max",
    "handles": {
      "leetcode": "I8bRKA2K9C",
      "atcoder": "",
      "codeforces": "",
      "hackerrank": "Jayakrishnan5029",
      "github": "jaikrishnan-max",
      "skillrack": "I8bRKA2K9C"
    }
  },
  {
    "id": 174,
    "name": "TANVEER UL HAQUE H",
    "github_link": "https://github.com/Theos7383",
    "handles": {
      "leetcode": "Tanveer_Official",
      "atcoder": "Theos",
      "codeforces": "",
      "hackerrank": "",
      "github": "Theos7383",
      "skillrack": "Tanveer_Official"
    }
  },
  {
    "id": 175,
    "name": "NISHA BRITTOLIN X I",
    "github_link": "https://github.com/NishaBrittolin04",
    "handles": {
      "leetcode": "NishaBrittolin",
      "atcoder": "NishaBrittolin",
      "codeforces": "Nisha_Brittolin",
      "hackerrank": "nishabrittolin15",
      "github": "NishaBrittolin04",
      "skillrack": "NishaBrittolin"
    }
  },
  {
    "id": 176,
    "name": "HEMA RAMACHANDRAN",
    "github_link": "https://github.com/HemaRamachandran28",
    "handles": {
      "leetcode": "Hema2809",
      "atcoder": "Hema2809",
      "codeforces": "",
      "hackerrank": "hemaaramachandr1",
      "github": "HemaRamachandran28",
      "skillrack": "Hema2809"
    }
  },
  {
    "id": 177,
    "name": "SREENITHY S S",
    "github_link": "https://github.com/Sreenithy22",
    "handles": {
      "leetcode": "J3zRCtM8Oz",
      "atcoder": "Sreenithy",
      "codeforces": "sreenithy17",
      "hackerrank": "sreenithy17",
      "github": "Sreenithy22",
      "skillrack": "J3zRCtM8Oz"
    }
  },
  {
    "id": 178,
    "name": "RAGHUL BALAJEE G K",
    "github_link": "https://github.com/nan",
    "handles": {
      "leetcode": "RagulBalajee",
      "atcoder": "RagulBalajee",
      "codeforces": "",
      "hackerrank": "",
      "github": "",
      "skillrack": "RagulBalajee"
    }
  },
  {
    "id": 179,
    "name": "KAAVIYAA SHREE S",
    "github_link": "https://github.com/Kaaviyaa-Shree",
    "handles": {
      "leetcode": "Kaaviyaa_Shree_S",
      "atcoder": "Kaaviyaa",
      "codeforces": "Kaaviyaa_Shree",
      "hackerrank": "shreekaaviyaa",
      "github": "Kaaviyaa-Shree",
      "skillrack": "Kaaviyaa_Shree_S"
    }
  },
  {
    "id": 180,
    "name": "SHRINITHI MAHALAKSHMI R",
    "github_link": "https://github.com/Shrinithi09",
    "handles": {
      "leetcode": "shrinithi09",
      "atcoder": "shrinithi09",
      "codeforces": "Shrinithi09",
      "hackerrank": "shrinithimahala1",
      "github": "Shrinithi09",
      "skillrack": "shrinithi09"
    }
  },
  {
    "id": 181,
    "name": "JEEVIA HARSHINI M",
    "github_link": "https://github.com/jeevia22",
    "handles": {
      "leetcode": "jeevia_22",
      "atcoder": "jeevia_22",
      "codeforces": "jeevia_22",
      "hackerrank": "jeevia22harshini",
      "github": "jeevia22",
      "skillrack": "jeevia_22"
    }
  },
  {
    "id": 182,
    "name": "VIMALRAJ R",
    "github_link": "https://github.com/Vimalraj-R",
    "handles": {
      "leetcode": "VimalrajR",
      "atcoder": "",
      "codeforces": "Vim_raj",
      "hackerrank": "rv1870713",
      "github": "Vimalraj-R",
      "skillrack": "VimalrajR"
    }
  },
  {
    "id": 183,
    "name": "SANDHIYA S",
    "github_link": "https://github.com/nan",
    "handles": {
      "leetcode": "sandhiya_saravanan_leetcode",
      "atcoder": "sandhiya18",
      "codeforces": "saravanansandhiya99",
      "hackerrank": "sandhiya_18",
      "github": "",
      "skillrack": "sandhiya_saravanan_leetcode"
    }
  },
  {
    "id": 184,
    "name": "DHARAN M J",
    "github_link": "https://github.com/DharanSJIT",
    "handles": {
      "leetcode": "Dharan_05",
      "atcoder": "Dharan",
      "codeforces": "",
      "hackerrank": "dharan_mj05",
      "github": "DharanSJIT",
      "skillrack": {
        "username": "Dharan_05",
        "id": "448197",
        "key": "656194276ad60969e76f11873a6191907b9604f4"
      }
    }
  },
  {
    "id": 185,
    "name": "JAIDEEP P S",
    "github_link": "https://github.com/nan",
    "handles": {
      "leetcode": "",
      "atcoder": "",
      "codeforces": "",
      "hackerrank": "psjaideep8",
      "github": "",
      "skillrack": "jaideepps"
    }
  },
  {
    "id": 186,
    "name": "YASIRA BEGUM K",
    "github_link": "https://github.com/nan",
    "handles": {
      "leetcode": "Yasira_Begum",
      "atcoder": "Yasira_Begum_K",
      "codeforces": "yasirakuthbudeen",
      "hackerrank": "",
      "github": "",
      "skillrack": "Yasira_Begum"
    }
  },
  {
    "id": 187,
    "name": "SHANKARA NARAYANAN M",
    "github_link": "https://github.com/Shankar280925",
    "handles": {
      "leetcode": "shankar2809",
      "atcoder": "Shankar280925",
      "codeforces": "shankar280925",
      "hackerrank": "shankar280925",
      "github": "Shankar280925",
      "skillrack": "shankar2809"
    }
  },
  {
    "id": 188,
    "name": "BHUVANESHWARI M",
    "github_link": "https://github.com/nan",
    "handles": {
      "leetcode": "BHUVANESHWARIMADESH",
      "atcoder": "",
      "codeforces": "",
      "hackerrank": "nasima365banu",
      "github": "",
      "skillrack": "BHUVANESHWARIMADESH"
    }
  },
  {
    "id": 189,
    "name": "ANCY EBISHA P",
    "github_link": "https://github.com/AncyEbishaP",
    "handles": {
      "leetcode": "",
      "atcoder": "",
      "codeforces": "",
      "hackerrank": "",
      "github": "AncyEbishaP",
      "skillrack": "ancyebishap"
    }
  },
  {
    "id": 190,
    "name": "ABIRAM D",
    "github_link": "https://github.com/ABIRAMDEVARAJI",
    "handles": {
      "leetcode": "BoI2yp6fuf",
      "atcoder": "",
      "codeforces": "",
      "hackerrank": "",
      "github": "ABIRAMDEVARAJI",
      "skillrack": "BoI2yp6fuf"
    }
  },
  {
    "id": 191,
    "name": "RAHUL  D",
    "github_link": "https://github.com/rahuldr556",
    "handles": {
      "leetcode": "rahuldr556",
      "atcoder": "Rahul_dev_01",
      "codeforces": "",
      "hackerrank": "rahuldr556",
      "github": "rahuldr556",
      "skillrack": "rahuldr556"
    }
  },
  {
    "id": 192,
    "name": "NASIMA BANU A",
    "github_link": "https://github.com/Nasima0306",
    "handles": {
      "leetcode": "nasima365banu",
      "atcoder": "nasimabanu",
      "codeforces": "nasima365banu",
      "hackerrank": "nasima365banu",
      "github": "Nasima0306",
      "skillrack": "nasima365banu"
    }
  },
  {
    "id": 193,
    "name": "AMAREESHVAR R",
    "github_link": "https://github.com/AMAREESHVAR018",
    "handles": {
      "leetcode": "AMAREESHVAR",
      "atcoder": "",
      "codeforces": "AMAREESHVAR",
      "hackerrank": "amar1016eeshvar",
      "github": "AMAREESHVAR018",
      "skillrack": "AMAREESHVAR"
    }
  },
  {
    "id": 194,
    "name": "KAVIYAMANI M",
    "github_link": "https://github.com/KAVIYAMANI-M",
    "handles": {
      "leetcode": "kaviyamanim2005",
      "atcoder": "KAVIYAMANI",
      "codeforces": "kaviyamanim2005",
      "hackerrank": "kaviyamanim2005",
      "github": "KAVIYAMANI-M",
      "skillrack": "kaviyamanim2005"
    }
  },
  {
    "id": 195,
    "name": "YUGA T",
    "github_link": "https://github.com/GitHub",
    "handles": {
      "leetcode": "",
      "atcoder": "",
      "codeforces": "",
      "hackerrank": "",
      "github": "",
      "skillrack": "yugat"
    }
  },
  {
    "id": 196,
    "name": "KISHORE A",
    "github_link": "https://github.com/Kishore-a77",
    "handles": {
      "leetcode": "kishoreachennai",
      "atcoder": "",
      "codeforces": "",
      "hackerrank": "",
      "github": "",
      "skillrack": "kishoreachennai"
    }
  },
  {
    "id": 197,
    "name": "ANANDA KUMARAN K I",
    "github_link": "https://github.com/nan",
    "handles": {
      "leetcode": "anandu44333",
      "atcoder": "",
      "codeforces": "",
      "hackerrank": "",
      "github": "",
      "skillrack": "anandu44333"
    }
  },
  {
    "id": 198,
    "name": "MAHANANDH THILAKAR VIMALA SATHEES KUMAR",
    "github_link": "https://github.com/Mahanandh?tab=repositories",
    "handles": {
      "leetcode": "Mahanandh",
      "atcoder": "Mahanandh777",
      "codeforces": "mahanandhthilakar07",
      "hackerrank": "mahanandhthilak1",
      "github": "",
      "skillrack": "Mahanandh"
    }
  },
  {
    "id": 199,
    "name": "KALIDASS L",
    "github_link": "https://github.com/Kalidass-05",
    "handles": {
      "leetcode": "Kalidass_1480",
      "atcoder": "Kalidass",
      "codeforces": "kalidasslakshmipathi",
      "hackerrank": "kalidasslakshmi1",
      "github": "Kalidass-05",
      "skillrack": "Kalidass_1480"
    }
  },
  {
    "id": 200,
    "name": "SANJAY SREERAM S",
    "github_link": "https://github.com/sanjaysreeram0701-bit",
    "handles": {
      "leetcode": "srisreeram",
      "atcoder": "sanjaysreeram07",
      "codeforces": "sanjaysreeram07",
      "hackerrank": "sanjaysreeram071",
      "github": "sanjaysreeram0701-bit",
      "skillrack": "srisreeram"
    }
  },
  {
    "id": 201,
    "name": "MONISHRAJ P",
    "github_link": "https://github.com/Monishrajpalanivelu",
    "handles": {
      "leetcode": "Monishrajpalanivelu",
      "atcoder": "Monishraj",
      "codeforces": "Monish10",
      "hackerrank": "monishrajpalani1",
      "github": "Monishrajpalanivelu",
      "skillrack": "Monishrajpalanivelu"
    }
  },
  {
    "id": 202,
    "name": "AGNES REMINA P",
    "github_link": "https://github.com/AGNESREMINA",
    "handles": {
      "leetcode": "VEF9SXyK62",
      "atcoder": "Agnes_Remina",
      "codeforces": "kausii",
      "hackerrank": "",
      "github": "AGNESREMINA",
      "skillrack": "VEF9SXyK62"
    }
  },
  {
    "id": 203,
    "name": "HANSIKA",
    "github_link": "https://github.com/nan",
    "handles": {
      "leetcode": "",
      "atcoder": "",
      "codeforces": "",
      "hackerrank": "",
      "github": "",
      "skillrack": "hansika"
    }
  },
  {
    "id": 204,
    "name": "KAUSIKA S",
    "github_link": "https://github.com/kausika18",
    "handles": {
      "leetcode": "kausika18",
      "atcoder": "Kausika",
      "codeforces": "kausii",
      "hackerrank": "santhanamarunth1",
      "github": "kausika18",
      "skillrack": "kausika18"
    }
  },
  {
    "id": 205,
    "name": "KEERTHANA M",
    "github_link": "https://github.com/mkeerthana-08 - Github",
    "handles": {
      "leetcode": "",
      "atcoder": "",
      "codeforces": "",
      "hackerrank": "5036_Keerthana",
      "github": "",
      "skillrack": "keerthanam"
    }
  },
  {
    "id": 206,
    "name": "SABARISH S",
    "github_link": "https://github.com/Datadeveloper03",
    "handles": {
      "leetcode": "stranger_2622",
      "atcoder": "sabarish",
      "codeforces": "",
      "hackerrank": "",
      "github": "Datadeveloper03",
      "skillrack": "stranger_2622"
    }
  },
  {
    "id": 207,
    "name": "SANJAY S",
    "github_link": "https://github.com/sanjay22-s",
    "handles": {
      "leetcode": "sjysanjay2211",
      "atcoder": "Sanjay22",
      "codeforces": "ssanjay2211",
      "hackerrank": "",
      "github": "sanjay22-s",
      "skillrack": "sjysanjay2211"
    }
  },
  {
    "id": 208,
    "name": "DINESH KARTHICK V",
    "github_link": "https://github.com/dineshkarthick50255",
    "handles": {
      "leetcode": "dineshkarthick282005",
      "atcoder": "dineshv",
      "codeforces": "dineshkarthick282005",
      "hackerrank": "dineshkarthick26",
      "github": "dineshkarthick50255",
      "skillrack": "dineshkarthick282005"
    }
  },
  {
    "id": 209,
    "name": "SUVISHA BRIGIL SUDHAKAR",
    "github_link": "https://github.com/suvisha28",
    "handles": {
      "leetcode": "suvishabrigil",
      "atcoder": "Suvisha28",
      "codeforces": "suvishabrigil28",
      "hackerrank": "suvishabrigil28",
      "github": "suvisha28",
      "skillrack": "suvishabrigil"
    }
  },
  {
    "id": 210,
    "name": "SARAVANAKUMAR T",
    "github_link": "https://github.com/Saravanakumar-T (Saravanakumar.T)",
    "handles": {
      "leetcode": "fLwC94tXnj",
      "atcoder": "",
      "codeforces": "",
      "hackerrank": "",
      "github": "",
      "skillrack": "fLwC94tXnj"
    }
  },
  {
    "id": 211,
    "name": "NAGA VINAY AVVARU",
    "github_link": "https://github.com/Vinay0905",
    "handles": {
      "leetcode": "nagavinay0905",
      "atcoder": "NagaVinay0905",
      "codeforces": "nagavinay0905",
      "hackerrank": "23ec1165",
      "github": "Vinay0905",
      "skillrack": "nagavinay0905"
    }
  },
  {
    "id": 212,
    "name": "DEEPALAKSHMI R",
    "github_link": "https://github.com/nan",
    "handles": {
      "leetcode": "Deepalakshmir",
      "atcoder": "deepalakshmiravi",
      "codeforces": "",
      "hackerrank": "",
      "github": "",
      "skillrack": "Deepalakshmir"
    }
  },
  {
    "id": 213,
    "name": "HARISH RAGAVENDAR M",
    "github_link": "https://github.com/Harish-4950",
    "handles": {
      "leetcode": "harishragavendar56",
      "atcoder": "",
      "codeforces": "",
      "hackerrank": "",
      "github": "",
      "skillrack": "harishragavendar56"
    }
  },
  {
    "id": 214,
    "name": "ANLIN ABISHEK J",
    "github_link": "https://github.com/Anlin-Abishek",
    "handles": {
      "leetcode": "Anlin_Abishek",
      "atcoder": "Anlin_abishek",
      "codeforces": "",
      "hackerrank": "anlin18abishek1",
      "github": "Anlin-Abishek",
      "skillrack": "Anlin_Abishek"
    }
  },
  {
    "id": 215,
    "name": "SRINANDHINEE M",
    "github_link": "https://github.com/Srinandhinee",
    "handles": {
      "leetcode": "Srinandhinee",
      "atcoder": "Srinandhinee_14",
      "codeforces": "Srinandhinee",
      "hackerrank": "srinandhinee_141",
      "github": "Srinandhinee",
      "skillrack": "Srinandhinee"
    }
  },
  {
    "id": 216,
    "name": "SARAVANAN NAGARAJAN",
    "github_link": "https://github.com/Cloud-6969 (Saravanan Nagarajan)",
    "handles": {
      "leetcode": "",
      "atcoder": "",
      "codeforces": "",
      "hackerrank": "sharanvbc",
      "github": "",
      "skillrack": "saravanannagarajan"
    }
  },
  {
    "id": 217,
    "name": "THANUJA S",
    "github_link": "https://github.com/Thanuja-07",
    "handles": {
      "leetcode": "thanujasasi145",
      "atcoder": "Thanuja_07",
      "codeforces": "",
      "hackerrank": "",
      "github": "Thanuja-07",
      "skillrack": "thanujasasi145"
    }
  },
  {
    "id": 218,
    "name": "DHIVYADHARSHINI V",
    "github_link": "https://github.com/DhivyadharshiniCoder",
    "handles": {
      "leetcode": "23CCE012",
      "atcoder": "dhivyadharshini",
      "codeforces": "",
      "hackerrank": "dhivyadharshan01",
      "github": "DhivyadharshiniCoder",
      "skillrack": "23CCE012"
    }
  },
  {
    "id": 219,
    "name": "SAARAH ZAYN",
    "github_link": "https://github.com/Saarah06",
    "handles": {
      "leetcode": "Zayn_06",
      "atcoder": "Zayn_06",
      "codeforces": "Zayn_06",
      "hackerrank": "Zayn_06",
      "github": "Saarah06",
      "skillrack": "Zayn_06"
    }
  },
  {
    "id": 220,
    "name": "LITISH KUMAR D",
    "github_link": "https://github.com/Litishkumar",
    "handles": {
      "leetcode": "OmDKipO1Al",
      "atcoder": "Litish",
      "codeforces": "Litish",
      "hackerrank": "litishk200613",
      "github": "Litishkumar",
      "skillrack": "OmDKipO1Al"
    }
  },
  {
    "id": 221,
    "name": "MARIA PETER RUFIN M",
    "github_link": "https://github.com/Peter-html",
    "handles": {
      "leetcode": "Peter_Rufin",
      "atcoder": "Peter_rufin",
      "codeforces": "Rufin",
      "hackerrank": "rufinmd23",
      "github": "Peter-html",
      "skillrack": "Peter_Rufin"
    }
  },
  {
    "id": 222,
    "name": "KANIESH NAIR",
    "github_link": "https://github.com/KanieshNairr",
    "handles": {
      "leetcode": "kanieshnairr",
      "atcoder": "KanieshNairR",
      "codeforces": "kanieshnairr3",
      "hackerrank": "kanieshnairr3",
      "github": "KanieshNairr",
      "skillrack": "kanieshnairr"
    }
  },
  {
    "id": 223,
    "name": "Panbhu arasane A",
    "github_link": "https://github.com/Panbhuarasane-A",
    "handles": {
      "leetcode": "panbhu234",
      "atcoder": "",
      "codeforces": "",
      "hackerrank": "",
      "github": "Panbhuarasane-A",
      "skillrack": "panbhu234"
    }
  },
  {
    "id": 224,
    "name": "Sandhiya K",
    "github_link": "https://github.com/sandhiya-it",
    "handles": {
      "leetcode": "SANDHIYA_2005K",
      "atcoder": "Sandhiya_2005",
      "codeforces": "sandhiyakumarasamy73",
      "hackerrank": "5191_SandhiyaK",
      "github": "sandhiya-it",
      "skillrack": "SANDHIYA_2005K"
    }
  },
  {
    "id": 225,
    "name": "Abishek Lawrence",
    "github_link": "https://github.com/abishekLawrence47",
    "handles": {
      "leetcode": "ABISHEK_L",
      "atcoder": "abishek_47",
      "codeforces": "abi_47",
      "hackerrank": "abisheklawrence2",
      "github": "abishekLawrence47",
      "skillrack": "ABISHEK_L"
    }
  },
  {
    "id": 226,
    "name": "Pavithra J",
    "github_link": "https://github.com/Pavithra-Jayapal",
    "handles": {
      "leetcode": "Pavithra_Jayapal",
      "atcoder": "Pavithra_Jayapal",
      "codeforces": "Pavithra_Jayapal",
      "hackerrank": "pavithrajayapal1",
      "github": "Pavithra-Jayapal",
      "skillrack": "Pavithra_Jayapal"
    }
  }
]